{
  "id": 147,
  "frame_count": 47,
  "frame_width": 50,
  "frame_height": 64,
  "sheet_width": 2350,
  "sheet_height": 64,
  "delays": [
    30,
    30,
    30,
    30,
    30,
    30,
    30,
    30,
    30,
    30,
    30,
    30,
    30,
    30,
    30,
    30,
    30,
    30,
    30,
    30,
    30,
    30,
    30,
    30,
    30,
    30,
    30,
    30,
    30,
    30,
    30,
    30,
    30,
    30,
    30,
    30,
    30,
    30,
    30,
    30,
    30,
    30,
    30,
    30,
    30,
    30,
    30
  ]
}