{
  "id": 258,
  "frame_count": 50,
  "frame_width": 60,
  "frame_height": 64,
  "sheet_width": 3000,
  "sheet_height": 64,
  "delays": [
    30,
    30,
    30,
    30,
    30,
    30,
    30,
    30,
    30,
    30,
    30,
    30,
    30,
    30,
    30,
    30,
    30,
    30,
    30,
    30,
    30,
    30,
    30,
    30,
    30,
    30,
    30,
    30,
    30,
    30,
    30,
    30,
    30,
    30,
    30,
    30,
    30,
    30,
    30,
    30,
    30,
    30,
    30,
    30,
    30,
    30,
    30,
    30,
    30,
    30
  ]
}