{
  "id": 390,
  "frame_count": 55,
  "frame_width": 44,
  "frame_height": 72,
  "sheet_width": 2420,
  "sheet_height": 72,
  "delays": [
    30,
    30,
    30,
    30,
    30,
    30,
    30,
    30,
    30,
    30,
    30,
    30,
    30,
    30,
    30,
    30,
    30,
    30,
    30,
    30,
    30,
    30,
    30,
    30,
    30,
    30,
    30,
    30,
    30,
    30,
    30,
    30,
    30,
    30,
    30,
    30,
    30,
    30,
    30,
    30,
    30,
    30,
    30,
    30,
    30,
    30,
    30,
    30,
    30,
    30,
    30,
    30,
    30,
    30,
    30
  ]
}