{
  "id": 622,
  "frame_count": 59,
  "frame_width": 47,
  "frame_height": 65,
  "sheet_width": 2773,
  "sheet_height": 65,
  "delays": [
    30,
    30,
    30,
    30,
    30,
    30,
    30,
    30,
    30,
    30,
    30,
    30,
    30,
    30,
    30,
    30,
    30,
    30,
    30,
    30,
    30,
    30,
    30,
    30,
    30,
    30,
    30,
    30,
    30,
    30,
    30,
    30,
    30,
    30,
    30,
    30,
    30,
    30,
    30,
    30,
    30,
    30,
    30,
    30,
    30,
    30,
    30,
    30,
    30,
    30,
    30,
    30,
    30,
    30,
    30,
    30,
    30,
    30,
    30
  ]
}