{
  "id": 585,
  "frame_count": 59,
  "frame_width": 52,
  "frame_height": 70,
  "sheet_width": 3068,
  "sheet_height": 70,
  "delays": [
    40,
    40,
    40,
    40,
    40,
    40,
    40,
    40,
    40,
    40,
    40,
    40,
    40,
    40,
    40,
    40,
    40,
    40,
    40,
    40,
    40,
    40,
    40,
    40,
    40,
    40,
    40,
    40,
    40,
    40,
    40,
    40,
    40,
    40,
    40,
    40,
    40,
    40,
    40,
    40,
    40,
    40,
    40,
    40,
    40,
    40,
    40,
    40,
    40,
    40,
    40,
    40,
    40,
    40,
    40,
    40,
    40,
    40,
    40
  ]
}