{
  "id": 103,
  "frame_count": 48,
  "frame_width": 142,
  "frame_height": 99,
  "sheet_width": 6816,
  "sheet_height": 99,
  "delays": [
    40,
    40,
    40,
    40,
    40,
    40,
    40,
    40,
    40,
    40,
    40,
    40,
    40,
    40,
    40,
    40,
    40,
    40,
    40,
    40,
    40,
    40,
    40,
    40,
    40,
    40,
    40,
    40,
    40,
    40,
    40,
    40,
    40,
    40,
    40,
    40,
    40,
    40,
    40,
    40,
    40,
    40,
    40,
    40,
    40,
    40,
    40,
    40
  ]
}