{
  "id": 219,
  "frame_count": 60,
  "frame_width": 67,
  "frame_height": 70,
  "sheet_width": 4020,
  "sheet_height": 70,
  "delays": [
    40,
    40,
    40,
    40,
    40,
    40,
    40,
    40,
    40,
    40,
    40,
    40,
    40,
    40,
    40,
    40,
    40,
    40,
    40,
    40,
    40,
    40,
    40,
    40,
    40,
    40,
    40,
    40,
    40,
    40,
    40,
    40,
    40,
    40,
    40,
    40,
    40,
    40,
    40,
    40,
    40,
    40,
    40,
    40,
    40,
    40,
    40,
    40,
    40,
    40,
    40,
    40,
    40,
    40,
    40,
    40,
    40,
    40,
    40,
    40
  ]
}